flask_restful_swagger_2/deprecated_swagger.py
flask_restful_swagger_2/swagger.py
flask_restful_swagger_2/__init__.py
flask_restful_swagger_2-0.20.dist-info/RECORD
flask_restful_swagger_2-0.20.dist-info/DESCRIPTION.rst
flask_restful_swagger_2-0.20.dist-info/top_level.txt
flask_restful_swagger_2-0.20.dist-info/METADATA
flask_restful_swagger_2-0.20.dist-info/metadata.json
flask_restful_swagger_2-0.20.dist-info/WHEEL
