Metadata-Version: 2.0
Name: flask-restful-swagger-2
Version: 0.20
Summary: Extract swagger specs from your flask-restful project. Project based on flask-restful-swagger by Ran Tavory.
Home-page: https://github.com/swege/flask-restful-swagger-2.0
Author: Soeren Wegener
Author-email: UNKNOWN
License: MIT
Platform: UNKNOWN
Requires-Dist: Flask-RESTful (>=0.2.12)
